setup.cfg
setup.py
froglet/__init__.py
froglet/froglet.py
froglet.egg-info/PKG-INFO
froglet.egg-info/SOURCES.txt
froglet.egg-info/dependency_links.txt
froglet.egg-info/not-zip-safe
froglet.egg-info/top_level.txt