Metadata-Version: 1.0
Name: froglet
Version: 0.3
Summary: Client for Frog server
Home-page: https://github.com/hslatman/froglet
Author: Herman Slatman
Author-email: mail@hermanslatman.nl
License: GPLv3
Platform: UNKNOWN
